varyzhoutest01/__init__.py
varyzhoutest01/test01.py
varyzhoutest01-0.0.1.dist-info/LICENSE
varyzhoutest01-0.0.1.dist-info/METADATA
varyzhoutest01-0.0.1.dist-info/WHEEL
varyzhoutest01-0.0.1.dist-info/top_level.txt
varyzhoutest01-0.0.1.dist-info/RECORD
